<DOMSymbolItem xmlns:xsi="http://www.w3.org/2001/XMLSchema-instance" xmlns="http://ns.adobe.com/xfl/2008/" name="AppSelector" itemID="4eecc29e-000007e4" linkageExportForAS="true" linkageClassName="gfx_applications_view" lastModified="1387666207" lastUniqueIdentifier="4">
  <timeline>
    <DOMTimeline name="AppSelector">
      <layers>
        <DOMLayer name="preloader" color="#FF800A" current="true" isSelected="true" autoNamed="false">
          <frames>
            <DOMFrame index="0" keyMode="9728">
              <elements>
                <DOMSymbolInstance libraryItemName="Common Assets/Symbol 241" name="preloader">
                  <matrix>
                    <Matrix a="0.89208984375" d="0.89208984375"/>
                  </matrix>
                  <transformationPoint>
                    <Point/>
                  </transformationPoint>
                  <color>
                    <Color tintMultiplier="0.44" tintColor="#0A485C"/>
                  </color>
                </DOMSymbolInstance>
              </elements>
            </DOMFrame>
          </frames>
        </DOMLayer>
        <DOMLayer name="infoField" color="#9933CC" locked="true" autoNamed="false">
          <frames>
            <DOMFrame index="0" keyMode="9728">
              <elements>
                <DOMDynamicText name="infoField" width="196.5" height="28.4" antiAliasSharpness="-25" antiAliasThickness="-25" isSelectable="false" renderAsHTML="true" lineType="multiline">
                  <matrix>
                    <Matrix tx="2" ty="2"/>
                  </matrix>
                  <textRuns>
                    <DOMTextRun>
                      <characters>Отметьте рабочие или&#xD;игнорируемые приложения</characters>
                      <textAttrs>
                        <DOMTextAttrs alignment="center" aliasText="false" lineSpacing="-1" bitmapSize="240" face="MyriadPro-Semibold" fillColor="#5E6064"/>
                      </textAttrs>
                    </DOMTextRun>
                  </textRuns>
                </DOMDynamicText>
              </elements>
            </DOMFrame>
          </frames>
        </DOMLayer>
      </layers>
    </DOMTimeline>
  </timeline>
</DOMSymbolItem>