<DOMSymbolItem xmlns:xsi="http://www.w3.org/2001/XMLSchema-instance" xmlns="http://ns.adobe.com/xfl/2008/" name="Symbol 157" itemID="4d416c76-000003b8" lastModified="1296133290">
  <timeline>
    <DOMTimeline name="Symbol 157">
      <layers>
        <DOMLayer name="z026_bmp" color="#4FFF4F" autoNamed="false" visible="false" layerType="guide">
          <frames>
            <DOMFrame index="0" keyMode="9728">
              <elements>
                <DOMBitmapInstance selected="true" libraryItemName="z026.png">
                  <matrix>
                    <Matrix tx="-102"/>
                  </matrix>
                </DOMBitmapInstance>
              </elements>
            </DOMFrame>
          </frames>
        </DOMLayer>
        <DOMLayer name="z026_slices" color="#9933CC" current="true" isSelected="true" autoNamed="false">
          <frames>
            <DOMFrame index="0" keyMode="9728">
              <elements>
                <DOMRectangleObject objectWidth="13.05" objectHeight="13.25" x="-102" y="0" selected="true" lockFlag="true">
                  <fill>
                    <BitmapFill bitmapPath="z026.png">
                      <matrix>
                        <Matrix a="20" d="20" tx="-102"/>
                      </matrix>
                    </BitmapFill>
                  </fill>
                </DOMRectangleObject>
                <DOMRectangleObject objectWidth="177.2" objectHeight="13.25" x="-88.95" y="0" selected="true" lockFlag="true">
                  <fill>
                    <BitmapFill bitmapPath="z026.png">
                      <matrix>
                        <Matrix a="20" d="20" tx="-102"/>
                      </matrix>
                    </BitmapFill>
                  </fill>
                </DOMRectangleObject>
                <DOMRectangleObject objectWidth="13.75" objectHeight="13.25" x="88.25" y="0" selected="true" lockFlag="true">
                  <fill>
                    <BitmapFill bitmapPath="z026.png">
                      <matrix>
                        <Matrix a="20" d="20" tx="-102"/>
                      </matrix>
                    </BitmapFill>
                  </fill>
                </DOMRectangleObject>
                <DOMRectangleObject objectWidth="13.05" objectHeight="108" x="-102" y="13.25" selected="true" lockFlag="true">
                  <fill>
                    <BitmapFill bitmapPath="z026.png">
                      <matrix>
                        <Matrix a="20" d="20" tx="-102"/>
                      </matrix>
                    </BitmapFill>
                  </fill>
                </DOMRectangleObject>
                <DOMRectangleObject objectWidth="177.2" objectHeight="108" x="-88.95" y="13.25" selected="true" lockFlag="true">
                  <fill>
                    <BitmapFill bitmapPath="z026.png">
                      <matrix>
                        <Matrix a="20" d="20" tx="-102"/>
                      </matrix>
                    </BitmapFill>
                  </fill>
                </DOMRectangleObject>
                <DOMRectangleObject objectWidth="13.75" objectHeight="108" x="88.25" y="13.25" selected="true" lockFlag="true">
                  <fill>
                    <BitmapFill bitmapPath="z026.png">
                      <matrix>
                        <Matrix a="20" d="20" tx="-102"/>
                      </matrix>
                    </BitmapFill>
                  </fill>
                </DOMRectangleObject>
                <DOMRectangleObject objectWidth="13.05" objectHeight="13.75" x="-102" y="121.25" selected="true" lockFlag="true">
                  <fill>
                    <BitmapFill bitmapPath="z026.png">
                      <matrix>
                        <Matrix a="20" d="20" tx="-102"/>
                      </matrix>
                    </BitmapFill>
                  </fill>
                </DOMRectangleObject>
                <DOMRectangleObject objectWidth="177.2" objectHeight="13.75" x="-88.95" y="121.25" selected="true" lockFlag="true">
                  <fill>
                    <BitmapFill bitmapPath="z026.png">
                      <matrix>
                        <Matrix a="20" d="20" tx="-102"/>
                      </matrix>
                    </BitmapFill>
                  </fill>
                </DOMRectangleObject>
                <DOMRectangleObject objectWidth="13.75" objectHeight="13.75" x="88.25" y="121.25" selected="true" lockFlag="true">
                  <fill>
                    <BitmapFill bitmapPath="z026.png">
                      <matrix>
                        <Matrix a="20" d="20" tx="-102"/>
                      </matrix>
                    </BitmapFill>
                  </fill>
                </DOMRectangleObject>
              </elements>
            </DOMFrame>
          </frames>
        </DOMLayer>
      </layers>
    </DOMTimeline>
  </timeline>
</DOMSymbolItem>