<DOMSymbolItem xmlns:xsi="http://www.w3.org/2001/XMLSchema-instance" xmlns="http://ns.adobe.com/xfl/2008/" name="Common Assets/Symbol 151" itemID="52228947-000006a4" scaleGridLeft="-75.5" scaleGridRight="74.5" scaleGridTop="52" scaleGridBottom="156" lastModified="1296132654">
  <timeline>
    <DOMTimeline name="Symbol 151">
      <layers>
        <DOMLayer name="z024_bmp" color="#4FFF4F" autoNamed="false" visible="false" layerType="guide">
          <frames>
            <DOMFrame index="0" keyMode="9728">
              <elements>
                <DOMBitmapInstance selected="true" libraryItemName="Bitmap/z024.png">
                  <matrix>
                    <Matrix tx="-129"/>
                  </matrix>
                </DOMBitmapInstance>
              </elements>
            </DOMFrame>
          </frames>
        </DOMLayer>
        <DOMLayer name="z024_slices" color="#9933CC" current="true" isSelected="true" autoNamed="false">
          <frames>
            <DOMFrame index="0" keyMode="9728">
              <elements>
                <DOMRectangleObject objectWidth="53.55" objectHeight="52" x="-129" y="0" lockFlag="true">
                  <fill>
                    <BitmapFill bitmapPath="Bitmap/z024.png">
                      <matrix>
                        <Matrix a="20" d="20" tx="-129"/>
                      </matrix>
                    </BitmapFill>
                  </fill>
                </DOMRectangleObject>
                <DOMRectangleObject objectWidth="149.95" objectHeight="52" x="-75.45" y="0" lockFlag="true">
                  <fill>
                    <BitmapFill bitmapPath="Bitmap/z024.png">
                      <matrix>
                        <Matrix a="20" d="20" tx="-129"/>
                      </matrix>
                    </BitmapFill>
                  </fill>
                </DOMRectangleObject>
                <DOMRectangleObject objectWidth="54.5" objectHeight="52" x="74.5" y="0" lockFlag="true">
                  <fill>
                    <BitmapFill bitmapPath="Bitmap/z024.png">
                      <matrix>
                        <Matrix a="20" d="20" tx="-129"/>
                      </matrix>
                    </BitmapFill>
                  </fill>
                </DOMRectangleObject>
                <DOMRectangleObject objectWidth="53.55" objectHeight="104" x="-129" y="52" lockFlag="true">
                  <fill>
                    <BitmapFill bitmapPath="Bitmap/z024.png">
                      <matrix>
                        <Matrix a="20" d="20" tx="-129"/>
                      </matrix>
                    </BitmapFill>
                  </fill>
                </DOMRectangleObject>
                <DOMRectangleObject objectWidth="149.95" objectHeight="104" x="-75.45" y="52" selected="true" lockFlag="true">
                  <fill>
                    <BitmapFill bitmapPath="Bitmap/z024.png">
                      <matrix>
                        <Matrix a="20" d="20" tx="-129"/>
                      </matrix>
                    </BitmapFill>
                  </fill>
                </DOMRectangleObject>
                <DOMRectangleObject objectWidth="54.5" objectHeight="104" x="74.5" y="52" lockFlag="true">
                  <fill>
                    <BitmapFill bitmapPath="Bitmap/z024.png">
                      <matrix>
                        <Matrix a="20" d="20" tx="-129"/>
                      </matrix>
                    </BitmapFill>
                  </fill>
                </DOMRectangleObject>
                <DOMRectangleObject objectWidth="53.55" objectHeight="52" x="-129" y="156" lockFlag="true">
                  <fill>
                    <BitmapFill bitmapPath="Bitmap/z024.png">
                      <matrix>
                        <Matrix a="20" d="20" tx="-129"/>
                      </matrix>
                    </BitmapFill>
                  </fill>
                </DOMRectangleObject>
                <DOMRectangleObject objectWidth="149.95" objectHeight="52" x="-75.45" y="156" lockFlag="true">
                  <fill>
                    <BitmapFill bitmapPath="Bitmap/z024.png">
                      <matrix>
                        <Matrix a="20" d="20" tx="-129"/>
                      </matrix>
                    </BitmapFill>
                  </fill>
                </DOMRectangleObject>
                <DOMRectangleObject objectWidth="54.5" objectHeight="52" x="74.5" y="156" lockFlag="true">
                  <fill>
                    <BitmapFill bitmapPath="Bitmap/z024.png">
                      <matrix>
                        <Matrix a="20" d="20" tx="-129"/>
                      </matrix>
                    </BitmapFill>
                  </fill>
                </DOMRectangleObject>
              </elements>
            </DOMFrame>
          </frames>
        </DOMLayer>
      </layers>
    </DOMTimeline>
  </timeline>
</DOMSymbolItem>